{"programme":{"type":"episode","pid":"p008gs0c","expected_child_count":null,"position":null,"media_type":null,"title":"The Families of Manshiyet Nasser","short_synopsis":"Life after a deadly rockslide in one of Cairo's biggest slums, Manshiyet Nasser.","medium_synopsis":"Manshiyet Nasser is one of Cairo's biggest slums. In 2008 a massive rockslide swept away dozens of homes killing over 100 people. Assignment finds out what happened to the families in the area.","long_synopsis":"In September 2008 huge boulders rained down on the Manshiyet Nasser slum in Cairo. \n\nThe slum had built up at the foot of the steep slopes of the Mokattam Hill in the centre of Cairo. At least 107 people died in the disaster but it is believed many more were buried beneath the rocks. \n\nIn the wake of the disaster, the government promised to re-house people away from the danger of the rocks into modern homes. \n\nTwo years on the re-housing policy has proved controversial and, according to the slum dwellers, inadequate.\n\nFor Assignment Catherine Miller spends time with families in Manshiyet Nasser.","first_broadcast_date":"2010-07-08T12:05:00+01:00","display_title":{"title":"Assignment ","subtitle":"The Families of Manshiyet Nasser"},"ownership":{"service":{"type":"radio","id":"bbc_world_service","key":"worldservice","title":"BBC World Service"}},"parent":{"programme":{"type":"brand","pid":"p002vsn0","title":"Assignment ","short_synopsis":"Investigations and journeys into the heart of global events from BBC correspondents","position":null,"expected_child_count":null,"first_broadcast_date":"2008-05-10T11:06:00+01:00","ownership":{"service":{"type":"radio","id":"bbc_world_service","key":"worldservice","title":"BBC World Service"}}}},"peers":{"previous":{"type":"episode","pid":"p0089chm","title":"Arizona's Immigration Law SB1070","first_broadcast_date":"2010-07-01T12:05:00+01:00","position":null,"media_type":null},"next":{"type":"episode","pid":"p008jjnj","title":"Building Haiti better","first_broadcast_date":"2010-07-15T09:05:00+01:00","position":null,"media_type":null}},"versions":[{"canonical":1,"pid":"p008gs31","duration":1500,"types":["Original version"]}],"links":[{"type":"related_site","title":"Pain haunts Cairo rockfall slum","url":"http://news.bbc.co.uk/1/hi/world/middle_east/7608605.stm"}],"supporting_content_items":[],"available_clips":[],"categories":[{"type":"subject","id":"p009cjvz","key":"cairo_landslide","title":"2008 Cairo landslide","narrower":[],"broader":{},"has_topic_page":false,"sameAs":"http://dbpedia.org/resource/2008_Cairo_landslide"},{"type":"place","id":"p007lm7n","key":"cairo","title":"Cairo","narrower":[],"broader":{},"has_topic_page":true,"sameAs":"http://dbpedia.org/resource/Cairo"},{"type":"format","id":"PT006","key":"documentaries","title":"Documentaries","narrower":[],"broader":{},"has_topic_page":false,"sameAs":null},{"type":"place","id":"p009cjvx","key":"manshiyat_naser","title":"Manshiyat naser","narrower":[],"broader":{},"has_topic_page":false,"sameAs":"http://dbpedia.org/resource/Manshiyat_naser"},{"type":"place","id":"p009cjw2","key":"mokattam","title":"Mokattam","narrower":[],"broader":{},"has_topic_page":false,"sameAs":"http://dbpedia.org/resource/Mokattam"},{"type":"genre","id":"C00079","key":"news","title":"News","narrower":[],"broader":{},"has_topic_page":false,"sameAs":null},{"type":"subject","id":"p007lkbd","key":"slums","title":"Slum","narrower":[],"broader":{},"has_topic_page":true,"sameAs":"http://dbpedia.org/resource/Slum"}]}}