[{"score": 0.0011335272995458539, "link": "http://dbpedia.org/resource/Slavery"}, {"score": 0.0010813231284771978, "link": "http://dbpedia.org/resource/Play_%28theatre%29"}, {"score": 0.00076809034526903648, "link": "http://dbpedia.org/resource/Church_%28building%29"}, {"score": 0.00073608097694012934, "link": "http://dbpedia.org/resource/Charle"}, {"score": 0.00062059505356941956, "link": "http://dbpedia.org/resource/Worship"}, {"score": 0.0005679269234097514, "link": "http://dbpedia.org/resource/Referee"}, {"score": 0.00054083358207464359, "link": "http://dbpedia.org/resource/Sermon"}, {"score": 0.00048709168060862088, "link": "http://dbpedia.org/resource/Pastor"}, {"score": 0.00039369266084183987, "link": "http://dbpedia.org/resource/Culture"}, {"score": 0.00037544585130835575, "link": "http://dbpedia.org/resource/Baptists"}, {"score": 0.00037536966655294724, "link": "http://dbpedia.org/resource/African_American"}, {"score": 0.00034460557139262597, "link": "http://dbpedia.org/resource/Africa"}, {"score": 0.0003252870595351985, "link": "http://dbpedia.org/resource/Atlanta"}, {"score": 0.00032320230942884819, "link": "http://dbpedia.org/resource/Emotion"}, {"score": 0.00032077600594066397, "link": "http://dbpedia.org/resource/Shoal"}, {"score": 0.0003164091186729466, "link": "http://dbpedia.org/resource/Homework"}, {"score": 0.00031484245178204219, "link": "http://dbpedia.org/resource/Habitat"}, {"score": 0.00030351876134817696, "link": "http://dbpedia.org/resource/Herd"}, {"score": 0.00027847478445875616, "link": "http://dbpedia.org/resource/Large_White"}, {"score": 0.00027307461495740915, "link": "http://dbpedia.org/resource/Children%27s_games_%28role_play%29"}]